COPYING
MANIFEST.in
README.html
README.rst
example.pmg
partmgr-gui
partmgr-win.bat
requirements.txt
setup.py
doc/foreign-licenses/PYTHON-LICENSE.txt
doc/foreign-licenses/README
maintenance/cleantree.sh
maintenance/mkvenv-pyside.sh
maintenance/win-install-dependencies.cmd
maintenance/win-standalone-build.cmd
partmgr/__init__.py
partmgr/qt_bindings.py
partmgr.egg-info/PKG-INFO
partmgr.egg-info/SOURCES.txt
partmgr.egg-info/dependency_links.txt
partmgr.egg-info/requires.txt
partmgr.egg-info/top_level.txt
partmgr/core/__init__.py
partmgr/core/category.py
partmgr/core/database.py
partmgr/core/entity.py
partmgr/core/exception.py
partmgr/core/footprint.py
partmgr/core/image.py
partmgr/core/location.py
partmgr/core/origin.py
partmgr/core/parameter.py
partmgr/core/part.py
partmgr/core/stockitem.py
partmgr/core/storage.py
partmgr/core/supplier.py
partmgr/core/timestamp.py
partmgr/core/util.py
partmgr/core/version.py
partmgr/gui/__init__.py
partmgr/gui/entitycombobox.py
partmgr/gui/entitymanage.py
partmgr/gui/footprintmanage.py
partmgr/gui/footprintselect.py
partmgr/gui/globalstats.py
partmgr/gui/groupselect.py
partmgr/gui/itemselect.py
partmgr/gui/locationmanage.py
partmgr/gui/mainwindow.py
partmgr/gui/originselect.py
partmgr/gui/parametermanage.py
partmgr/gui/partmanage.py
partmgr/gui/partselect.py
partmgr/gui/partstoorder.py
partmgr/gui/pricefetch.py
partmgr/gui/protected_combobox.py
partmgr/gui/protected_doublespinbox.py
partmgr/gui/protected_lineedit.py
partmgr/gui/protected_spinbox.py
partmgr/gui/protected_widget.py
partmgr/gui/quantity.py
partmgr/gui/stockitem.py
partmgr/gui/storageselect.py
partmgr/gui/suppliermanage.py
partmgr/gui/tree.py
partmgr/gui/util.py
partmgr/pricefetch/__init__.py
partmgr/pricefetch/conrad.py
partmgr/pricefetch/pollin.py
partmgr/pricefetch/pricefetch.py
partmgr/pricefetch/reichelt.py
tests/__init__.py
tests/partmgr_tstlib.py
tests/run.sh
tests/test_pricefetch.py