Metadata-Version: 2.1
Name: partmgr
Version: 0.2
Summary: Part manager
Home-page: http://bues.ch/h/partmgr
Author: Michael Buesch
Author-email: m@bues.ch
License: GNU General Public License v2 or later
License-File: COPYING
